tf_levenberg_marquardt/__init__.py
tf_levenberg_marquardt/damping.py
tf_levenberg_marquardt/loss.py
tf_levenberg_marquardt/model.py
tf_levenberg_marquardt/training.py
tf_levenberg_marquardt-1.0.3.dist-info/LICENSE
tf_levenberg_marquardt-1.0.3.dist-info/METADATA
tf_levenberg_marquardt-1.0.3.dist-info/WHEEL
tf_levenberg_marquardt-1.0.3.dist-info/top_level.txt
tf_levenberg_marquardt-1.0.3.dist-info/RECORD
