Metadata-Version: 2.2
Name: tf-levenberg-marquardt
Version: 1.0.3
Summary: Tensorflow implementation of Levenberg-Marquardt training algorithm
Author-email: Fabio Di Marco <fabiodimarco@hotmail.it>
Maintainer-email: Fabio Di Marco <fabiodimarco@hotmail.it>
License: MIT License
Project-URL: Home-page, https://github.com/fabiodimarco/tf-levenberg-marquardt
Project-URL: Bug Reports, https://github.com/fabiodimarco/tf-levenberg-marquardt/issues
Project-URL: Source, https://github.com/fabiodimarco/tf-levenberg-marquardt/
Keywords: tensorflow,optimization,levenberg-marquardt,gauss-newton,training,numerical optimization,nonlinear least squares,second-order methods
Classifier: Development Status :: 4 - Beta
Classifier: Intended Audience :: Developers
Classifier: Topic :: Scientific/Engineering :: Artificial Intelligence
Classifier: License :: OSI Approved :: MIT License
Classifier: Programming Language :: Python :: 3
Classifier: Programming Language :: Python :: 3.9
Classifier: Programming Language :: Python :: 3.10
Classifier: Programming Language :: Python :: 3.11
Requires-Python: >=3.10
License-File: LICENSE
Requires-Dist: numpy>=1.22
Requires-Dist: tensorflow>=2.15.0
